<?xml version="1.0" encoding="utf-8"?>
	<annotation>
		<folder>VOC2007</folder>
		<filename>30974.jpg</filename>
		<size>
			<width>720</width>
			<height>405</height>
			<depth>3</depth>
		</size>
		<segmented>0</segmented>
		<object>
			<name>seaurchin</name>
			<pose>Rear</pose>
			<truncated>0</truncated>
			<difficult>0</difficult>
			<bndbox>
				<xmin>155</xmin>
				<ymin>116</ymin>
				<xmax>289</xmax>
				<ymax>250</ymax>
			</bndbox>
		</object>
		<object>
			<name>scallop</name>
			<pose>Rear</pose>
			<truncated>0</truncated>
			<difficult>0</difficult>
			<bndbox>
				<xmin>0</xmin>
				<ymin>168</ymin>
				<xmax>74</xmax>
				<ymax>278</ymax>
			</bndbox>
		</object>
		<object>
			<name>seacucumber</name>
			<pose>Rear</pose>
			<truncated>0</truncated>
			<difficult>0</difficult>
			<bndbox>
				<xmin>137</xmin>
				<ymin>228</ymin>
				<xmax>380</xmax>
				<ymax>400</ymax>
			</bndbox>
		</object>
		<object>
			<name>scallop</name>
			<pose>Rear</pose>
			<truncated>0</truncated>
			<difficult>0</difficult>
			<bndbox>
				<xmin>54</xmin>
				<ymin>119</ymin>
				<xmax>177</xmax>
				<ymax>236</ymax>
			</bndbox>
		</object>
		<object>
			<name>scallop</name>
			<pose>Rear</pose>
			<truncated>0</truncated>
			<difficult>0</difficult>
			<bndbox>
				<xmin>79</xmin>
				<ymin>184</ymin>
				<xmax>223</xmax>
				<ymax>327</ymax>
			</bndbox>
		</object>
		<object>
			<name>scallop</name>
			<pose>Rear</pose>
			<truncated>0</truncated>
			<difficult>0</difficult>
			<bndbox>
				<xmin>271</xmin>
				<ymin>93</ymin>
				<xmax>425</xmax>
				<ymax>198</ymax>
			</bndbox>
		</object>
		<object>
			<name>seaurchin</name>
			<pose>Rear</pose>
			<truncated>0</truncated>
			<difficult>0</difficult>
			<bndbox>
				<xmin>0</xmin>
				<ymin>51</ymin>
				<xmax>21</xmax>
				<ymax>176</ymax>
			</bndbox>
		</object>
	</annotation>
