<?xml version="1.0" encoding="utf-8"?>
	<annotation>
		<folder>VOC2007</folder>
		<filename>31068.jpg</filename>
		<size>
			<width>720</width>
			<height>405</height>
			<depth>3</depth>
		</size>
		<segmented>0</segmented>
		<object>
			<name>scallop</name>
			<pose>Rear</pose>
			<truncated>0</truncated>
			<difficult>0</difficult>
			<bndbox>
				<xmin>42</xmin>
				<ymin>163</ymin>
				<xmax>293</xmax>
				<ymax>377</ymax>
			</bndbox>
		</object>
		<object>
			<name>seaurchin</name>
			<pose>Rear</pose>
			<truncated>0</truncated>
			<difficult>0</difficult>
			<bndbox>
				<xmin>229</xmin>
				<ymin>149</ymin>
				<xmax>480</xmax>
				<ymax>402</ymax>
			</bndbox>
		</object>
		<object>
			<name>scallop</name>
			<pose>Rear</pose>
			<truncated>0</truncated>
			<difficult>0</difficult>
			<bndbox>
				<xmin>394</xmin>
				<ymin>165</ymin>
				<xmax>631</xmax>
				<ymax>402</ymax>
			</bndbox>
		</object>
		<object>
			<name>scallop</name>
			<pose>Rear</pose>
			<truncated>0</truncated>
			<difficult>0</difficult>
			<bndbox>
				<xmin>243</xmin>
				<ymin>85</ymin>
				<xmax>419</xmax>
				<ymax>182</ymax>
			</bndbox>
		</object>
		<object>
			<name>seaurchin</name>
			<pose>Rear</pose>
			<truncated>0</truncated>
			<difficult>0</difficult>
			<bndbox>
				<xmin>110</xmin>
				<ymin>59</ymin>
				<xmax>268</xmax>
				<ymax>174</ymax>
			</bndbox>
		</object>
		<object>
			<name>scallop</name>
			<pose>Rear</pose>
			<truncated>0</truncated>
			<difficult>0</difficult>
			<bndbox>
				<xmin>289</xmin>
				<ymin>5</ymin>
				<xmax>427</xmax>
				<ymax>96</ymax>
			</bndbox>
		</object>
	</annotation>
