<?xml version="1.0" encoding="utf-8"?>
	<annotation>
		<folder>VOC2007</folder>
		<filename>42124.jpg</filename>
		<size>
			<width>720</width>
			<height>405</height>
			<depth>3</depth>
		</size>
		<segmented>0</segmented>
		<object>
			<name>seacucumber</name>
			<pose>Rear</pose>
			<truncated>0</truncated>
			<difficult>0</difficult>
			<bndbox>
				<xmin>593</xmin>
				<ymin>157</ymin>
				<xmax>646</xmax>
				<ymax>191</ymax>
			</bndbox>
		</object>
		<object>
			<name>seaurchin</name>
			<pose>Rear</pose>
			<truncated>0</truncated>
			<difficult>0</difficult>
			<bndbox>
				<xmin>686</xmin>
				<ymin>77</ymin>
				<xmax>718</xmax>
				<ymax>120</ymax>
			</bndbox>
		</object>
		<object>
			<name>scallop</name>
			<pose>Rear</pose>
			<truncated>0</truncated>
			<difficult>0</difficult>
			<bndbox>
				<xmin>404</xmin>
				<ymin>51</ymin>
				<xmax>461</xmax>
				<ymax>93</ymax>
			</bndbox>
		</object>
		<object>
			<name>seacucumber</name>
			<pose>Rear</pose>
			<truncated>0</truncated>
			<difficult>0</difficult>
			<bndbox>
				<xmin>470</xmin>
				<ymin>12</ymin>
				<xmax>542</xmax>
				<ymax>80</ymax>
			</bndbox>
		</object>
		<object>
			<name>seacucumber</name>
			<pose>Rear</pose>
			<truncated>0</truncated>
			<difficult>0</difficult>
			<bndbox>
				<xmin>686</xmin>
				<ymin>106</ymin>
				<xmax>719</xmax>
				<ymax>140</ymax>
			</bndbox>
		</object>
		<object>
			<name>seaurchin</name>
			<pose>Rear</pose>
			<truncated>0</truncated>
			<difficult>0</difficult>
			<bndbox>
				<xmin>622</xmin>
				<ymin>45</ymin>
				<xmax>656</xmax>
				<ymax>91</ymax>
			</bndbox>
		</object>
		<object>
			<name>seacucumber</name>
			<pose>Rear</pose>
			<truncated>0</truncated>
			<difficult>0</difficult>
			<bndbox>
				<xmin>685</xmin>
				<ymin>147</ymin>
				<xmax>716</xmax>
				<ymax>217</ymax>
			</bndbox>
		</object>
		<object>
			<name>seacucumber</name>
			<pose>Rear</pose>
			<truncated>0</truncated>
			<difficult>0</difficult>
			<bndbox>
				<xmin>699</xmin>
				<ymin>113</ymin>
				<xmax>719</xmax>
				<ymax>164</ymax>
			</bndbox>
		</object>
		<object>
			<name>seacucumber</name>
			<pose>Rear</pose>
			<truncated>0</truncated>
			<difficult>0</difficult>
			<bndbox>
				<xmin>700</xmin>
				<ymin>112</ymin>
				<xmax>719</xmax>
				<ymax>152</ymax>
			</bndbox>
		</object>
		<object>
			<name>scallop</name>
			<pose>Rear</pose>
			<truncated>0</truncated>
			<difficult>0</difficult>
			<bndbox>
				<xmin>681</xmin>
				<ymin>66</ymin>
				<xmax>718</xmax>
				<ymax>106</ymax>
			</bndbox>
		</object>
		<object>
			<name>seacucumber</name>
			<pose>Rear</pose>
			<truncated>0</truncated>
			<difficult>0</difficult>
			<bndbox>
				<xmin>306</xmin>
				<ymin>89</ymin>
				<xmax>373</xmax>
				<ymax>163</ymax>
			</bndbox>
		</object>
		<object>
			<name>seacucumber</name>
			<pose>Rear</pose>
			<truncated>0</truncated>
			<difficult>0</difficult>
			<bndbox>
				<xmin>478</xmin>
				<ymin>7</ymin>
				<xmax>545</xmax>
				<ymax>53</ymax>
			</bndbox>
		</object>
	</annotation>
