<?xml version="1.0" encoding="utf-8"?>
	<annotation>
		<folder>VOC2007</folder>
		<filename>45915.jpg</filename>
		<size>
			<width>720</width>
			<height>405</height>
			<depth>3</depth>
		</size>
		<segmented>0</segmented>
		<object>
			<name>seacucumber</name>
			<pose>Rear</pose>
			<truncated>0</truncated>
			<difficult>0</difficult>
			<bndbox>
				<xmin>650</xmin>
				<ymin>385</ymin>
				<xmax>719</xmax>
				<ymax>403</ymax>
			</bndbox>
		</object>
		<object>
			<name>seaurchin</name>
			<pose>Rear</pose>
			<truncated>0</truncated>
			<difficult>0</difficult>
			<bndbox>
				<xmin>692</xmin>
				<ymin>341</ymin>
				<xmax>719</xmax>
				<ymax>382</ymax>
			</bndbox>
		</object>
		<object>
			<name>seaurchin</name>
			<pose>Rear</pose>
			<truncated>0</truncated>
			<difficult>0</difficult>
			<bndbox>
				<xmin>691</xmin>
				<ymin>379</ymin>
				<xmax>719</xmax>
				<ymax>402</ymax>
			</bndbox>
		</object>
		<object>
			<name>seaurchin</name>
			<pose>Rear</pose>
			<truncated>0</truncated>
			<difficult>0</difficult>
			<bndbox>
				<xmin>689</xmin>
				<ymin>374</ymin>
				<xmax>719</xmax>
				<ymax>403</ymax>
			</bndbox>
		</object>
		<object>
			<name>seaurchin</name>
			<pose>Rear</pose>
			<truncated>0</truncated>
			<difficult>0</difficult>
			<bndbox>
				<xmin>703</xmin>
				<ymin>321</ymin>
				<xmax>719</xmax>
				<ymax>366</ymax>
			</bndbox>
		</object>
		<object>
			<name>seaurchin</name>
			<pose>Rear</pose>
			<truncated>0</truncated>
			<difficult>0</difficult>
			<bndbox>
				<xmin>691</xmin>
				<ymin>371</ymin>
				<xmax>718</xmax>
				<ymax>403</ymax>
			</bndbox>
		</object>
		<object>
			<name>seaurchin</name>
			<pose>Rear</pose>
			<truncated>0</truncated>
			<difficult>0</difficult>
			<bndbox>
				<xmin>705</xmin>
				<ymin>298</ymin>
				<xmax>717</xmax>
				<ymax>336</ymax>
			</bndbox>
		</object>
		<object>
			<name>seaurchin</name>
			<pose>Rear</pose>
			<truncated>0</truncated>
			<difficult>0</difficult>
			<bndbox>
				<xmin>707</xmin>
				<ymin>328</ymin>
				<xmax>719</xmax>
				<ymax>368</ymax>
			</bndbox>
		</object>
		<object>
			<name>seaurchin</name>
			<pose>Rear</pose>
			<truncated>0</truncated>
			<difficult>0</difficult>
			<bndbox>
				<xmin>706</xmin>
				<ymin>234</ymin>
				<xmax>719</xmax>
				<ymax>273</ymax>
			</bndbox>
		</object>
		<object>
			<name>seaurchin</name>
			<pose>Rear</pose>
			<truncated>0</truncated>
			<difficult>0</difficult>
			<bndbox>
				<xmin>687</xmin>
				<ymin>326</ymin>
				<xmax>719</xmax>
				<ymax>369</ymax>
			</bndbox>
		</object>
		<object>
			<name>seacucumber</name>
			<pose>Rear</pose>
			<truncated>0</truncated>
			<difficult>0</difficult>
			<bndbox>
				<xmin>705</xmin>
				<ymin>114</ymin>
				<xmax>719</xmax>
				<ymax>177</ymax>
			</bndbox>
		</object>
		<object>
			<name>seacucumber</name>
			<pose>Rear</pose>
			<truncated>0</truncated>
			<difficult>0</difficult>
			<bndbox>
				<xmin>695</xmin>
				<ymin>21</ymin>
				<xmax>719</xmax>
				<ymax>78</ymax>
			</bndbox>
		</object>
		<object>
			<name>seacucumber</name>
			<pose>Rear</pose>
			<truncated>0</truncated>
			<difficult>0</difficult>
			<bndbox>
				<xmin>297</xmin>
				<ymin>369</ymin>
				<xmax>364</xmax>
				<ymax>403</ymax>
			</bndbox>
		</object>
		<object>
			<name>seacucumber</name>
			<pose>Rear</pose>
			<truncated>0</truncated>
			<difficult>0</difficult>
			<bndbox>
				<xmin>586</xmin>
				<ymin>383</ymin>
				<xmax>670</xmax>
				<ymax>403</ymax>
			</bndbox>
		</object>
		<object>
			<name>seaurchin</name>
			<pose>Rear</pose>
			<truncated>0</truncated>
			<difficult>0</difficult>
			<bndbox>
				<xmin>508</xmin>
				<ymin>357</ymin>
				<xmax>595</xmax>
				<ymax>403</ymax>
			</bndbox>
		</object>
		<object>
			<name>seacucumber</name>
			<pose>Rear</pose>
			<truncated>0</truncated>
			<difficult>0</difficult>
			<bndbox>
				<xmin>696</xmin>
				<ymin>106</ymin>
				<xmax>719</xmax>
				<ymax>136</ymax>
			</bndbox>
		</object>
		<object>
			<name>seaurchin</name>
			<pose>Rear</pose>
			<truncated>0</truncated>
			<difficult>0</difficult>
			<bndbox>
				<xmin>529</xmin>
				<ymin>229</ymin>
				<xmax>631</xmax>
				<ymax>309</ymax>
			</bndbox>
		</object>
		<object>
			<name>seacucumber</name>
			<pose>Rear</pose>
			<truncated>0</truncated>
			<difficult>0</difficult>
			<bndbox>
				<xmin>710</xmin>
				<ymin>143</ymin>
				<xmax>719</xmax>
				<ymax>191</ymax>
			</bndbox>
		</object>
		<object>
			<name>seaurchin</name>
			<pose>Rear</pose>
			<truncated>0</truncated>
			<difficult>0</difficult>
			<bndbox>
				<xmin>664</xmin>
				<ymin>386</ymin>
				<xmax>719</xmax>
				<ymax>403</ymax>
			</bndbox>
		</object>
		<object>
			<name>seacucumber</name>
			<pose>Rear</pose>
			<truncated>0</truncated>
			<difficult>0</difficult>
			<bndbox>
				<xmin>704</xmin>
				<ymin>284</ymin>
				<xmax>719</xmax>
				<ymax>345</ymax>
			</bndbox>
		</object>
		<object>
			<name>seacucumber</name>
			<pose>Rear</pose>
			<truncated>0</truncated>
			<difficult>0</difficult>
			<bndbox>
				<xmin>690</xmin>
				<ymin>247</ymin>
				<xmax>719</xmax>
				<ymax>292</ymax>
			</bndbox>
		</object>
		<object>
			<name>seacucumber</name>
			<pose>Rear</pose>
			<truncated>0</truncated>
			<difficult>0</difficult>
			<bndbox>
				<xmin>700</xmin>
				<ymin>231</ymin>
				<xmax>719</xmax>
				<ymax>270</ymax>
			</bndbox>
		</object>
		<object>
			<name>seacucumber</name>
			<pose>Rear</pose>
			<truncated>0</truncated>
			<difficult>0</difficult>
			<bndbox>
				<xmin>409</xmin>
				<ymin>135</ymin>
				<xmax>519</xmax>
				<ymax>198</ymax>
			</bndbox>
		</object>
		<object>
			<name>seacucumber</name>
			<pose>Rear</pose>
			<truncated>0</truncated>
			<difficult>0</difficult>
			<bndbox>
				<xmin>559</xmin>
				<ymin>383</ymin>
				<xmax>719</xmax>
				<ymax>403</ymax>
			</bndbox>
		</object>
		<object>
			<name>seaurchin</name>
			<pose>Rear</pose>
			<truncated>0</truncated>
			<difficult>0</difficult>
			<bndbox>
				<xmin>665</xmin>
				<ymin>279</ymin>
				<xmax>713</xmax>
				<ymax>353</ymax>
			</bndbox>
		</object>
		<object>
			<name>seaurchin</name>
			<pose>Rear</pose>
			<truncated>0</truncated>
			<difficult>0</difficult>
			<bndbox>
				<xmin>663</xmin>
				<ymin>368</ymin>
				<xmax>716</xmax>
				<ymax>403</ymax>
			</bndbox>
		</object>
		<object>
			<name>seaurchin</name>
			<pose>Rear</pose>
			<truncated>0</truncated>
			<difficult>0</difficult>
			<bndbox>
				<xmin>662</xmin>
				<ymin>386</ymin>
				<xmax>719</xmax>
				<ymax>403</ymax>
			</bndbox>
		</object>
		<object>
			<name>seacucumber</name>
			<pose>Rear</pose>
			<truncated>0</truncated>
			<difficult>0</difficult>
			<bndbox>
				<xmin>684</xmin>
				<ymin>371</ymin>
				<xmax>719</xmax>
				<ymax>403</ymax>
			</bndbox>
		</object>
		<object>
			<name>seaurchin</name>
			<pose>Rear</pose>
			<truncated>0</truncated>
			<difficult>0</difficult>
			<bndbox>
				<xmin>670</xmin>
				<ymin>123</ymin>
				<xmax>719</xmax>
				<ymax>164</ymax>
			</bndbox>
		</object>
		<object>
			<name>seaurchin</name>
			<pose>Rear</pose>
			<truncated>0</truncated>
			<difficult>0</difficult>
			<bndbox>
				<xmin>678</xmin>
				<ymin>220</ymin>
				<xmax>716</xmax>
				<ymax>278</ymax>
			</bndbox>
		</object>
		<object>
			<name>seaurchin</name>
			<pose>Rear</pose>
			<truncated>0</truncated>
			<difficult>0</difficult>
			<bndbox>
				<xmin>603</xmin>
				<ymin>380</ymin>
				<xmax>661</xmax>
				<ymax>403</ymax>
			</bndbox>
		</object>
		<object>
			<name>seacucumber</name>
			<pose>Rear</pose>
			<truncated>0</truncated>
			<difficult>0</difficult>
			<bndbox>
				<xmin>703</xmin>
				<ymin>131</ymin>
				<xmax>719</xmax>
				<ymax>212</ymax>
			</bndbox>
		</object>
		<object>
			<name>seacucumber</name>
			<pose>Rear</pose>
			<truncated>0</truncated>
			<difficult>0</difficult>
			<bndbox>
				<xmin>706</xmin>
				<ymin>244</ymin>
				<xmax>719</xmax>
				<ymax>352</ymax>
			</bndbox>
		</object>
		<object>
			<name>seaurchin</name>
			<pose>Rear</pose>
			<truncated>0</truncated>
			<difficult>0</difficult>
			<bndbox>
				<xmin>592</xmin>
				<ymin>75</ymin>
				<xmax>640</xmax>
				<ymax>113</ymax>
			</bndbox>
		</object>
		<object>
			<name>seaurchin</name>
			<pose>Rear</pose>
			<truncated>0</truncated>
			<difficult>0</difficult>
			<bndbox>
				<xmin>293</xmin>
				<ymin>204</ymin>
				<xmax>347</xmax>
				<ymax>255</ymax>
			</bndbox>
		</object>
		<object>
			<name>seaurchin</name>
			<pose>Rear</pose>
			<truncated>0</truncated>
			<difficult>0</difficult>
			<bndbox>
				<xmin>336</xmin>
				<ymin>160</ymin>
				<xmax>385</xmax>
				<ymax>207</ymax>
			</bndbox>
		</object>
		<object>
			<name>seacucumber</name>
			<pose>Rear</pose>
			<truncated>0</truncated>
			<difficult>0</difficult>
			<bndbox>
				<xmin>626</xmin>
				<ymin>308</ymin>
				<xmax>684</xmax>
				<ymax>403</ymax>
			</bndbox>
		</object>
		<object>
			<name>seacucumber</name>
			<pose>Rear</pose>
			<truncated>0</truncated>
			<difficult>0</difficult>
			<bndbox>
				<xmin>587</xmin>
				<ymin>181</ymin>
				<xmax>650</xmax>
				<ymax>278</ymax>
			</bndbox>
		</object>
		<object>
			<name>seacucumber</name>
			<pose>Rear</pose>
			<truncated>0</truncated>
			<difficult>0</difficult>
			<bndbox>
				<xmin>619</xmin>
				<ymin>119</ymin>
				<xmax>670</xmax>
				<ymax>166</ymax>
			</bndbox>
		</object>
		<object>
			<name>seaurchin</name>
			<pose>Rear</pose>
			<truncated>0</truncated>
			<difficult>0</difficult>
			<bndbox>
				<xmin>648</xmin>
				<ymin>164</ymin>
				<xmax>706</xmax>
				<ymax>205</ymax>
			</bndbox>
		</object>
		<object>
			<name>seacucumber</name>
			<pose>Rear</pose>
			<truncated>0</truncated>
			<difficult>0</difficult>
			<bndbox>
				<xmin>472</xmin>
				<ymin>73</ymin>
				<xmax>598</xmax>
				<ymax>123</ymax>
			</bndbox>
		</object>
		<object>
			<name>seaurchin</name>
			<pose>Rear</pose>
			<truncated>0</truncated>
			<difficult>0</difficult>
			<bndbox>
				<xmin>391</xmin>
				<ymin>277</ymin>
				<xmax>488</xmax>
				<ymax>362</ymax>
			</bndbox>
		</object>
		<object>
			<name>seacucumber</name>
			<pose>Rear</pose>
			<truncated>0</truncated>
			<difficult>0</difficult>
			<bndbox>
				<xmin>308</xmin>
				<ymin>111</ymin>
				<xmax>364</xmax>
				<ymax>152</ymax>
			</bndbox>
		</object>
		<object>
			<name>seacucumber</name>
			<pose>Rear</pose>
			<truncated>0</truncated>
			<difficult>0</difficult>
			<bndbox>
				<xmin>171</xmin>
				<ymin>124</ymin>
				<xmax>225</xmax>
				<ymax>168</ymax>
			</bndbox>
		</object>
		<object>
			<name>seacucumber</name>
			<pose>Rear</pose>
			<truncated>0</truncated>
			<difficult>0</difficult>
			<bndbox>
				<xmin>212</xmin>
				<ymin>168</ymin>
				<xmax>254</xmax>
				<ymax>235</ymax>
			</bndbox>
		</object>
	</annotation>
