<?xml version="1.0" encoding="utf-8"?>
	<annotation>
		<folder>VOC2007</folder>
		<filename>46027.jpg</filename>
		<size>
			<width>720</width>
			<height>405</height>
			<depth>3</depth>
		</size>
		<segmented>0</segmented>
		<object>
			<name>seaurchin</name>
			<pose>Rear</pose>
			<truncated>0</truncated>
			<difficult>0</difficult>
			<bndbox>
				<xmin>300</xmin>
				<ymin>335</ymin>
				<xmax>418</xmax>
				<ymax>403</ymax>
			</bndbox>
		</object>
		<object>
			<name>seacucumber</name>
			<pose>Rear</pose>
			<truncated>0</truncated>
			<difficult>0</difficult>
			<bndbox>
				<xmin>505</xmin>
				<ymin>354</ymin>
				<xmax>648</xmax>
				<ymax>403</ymax>
			</bndbox>
		</object>
		<object>
			<name>seaurchin</name>
			<pose>Rear</pose>
			<truncated>0</truncated>
			<difficult>0</difficult>
			<bndbox>
				<xmin>670</xmin>
				<ymin>353</ymin>
				<xmax>719</xmax>
				<ymax>403</ymax>
			</bndbox>
		</object>
		<object>
			<name>seacucumber</name>
			<pose>Rear</pose>
			<truncated>0</truncated>
			<difficult>0</difficult>
			<bndbox>
				<xmin>342</xmin>
				<ymin>210</ymin>
				<xmax>507</xmax>
				<ymax>314</ymax>
			</bndbox>
		</object>
		<object>
			<name>seacucumber</name>
			<pose>Rear</pose>
			<truncated>0</truncated>
			<difficult>0</difficult>
			<bndbox>
				<xmin>171</xmin>
				<ymin>295</ymin>
				<xmax>304</xmax>
				<ymax>394</ymax>
			</bndbox>
		</object>
		<object>
			<name>seacucumber</name>
			<pose>Rear</pose>
			<truncated>0</truncated>
			<difficult>0</difficult>
			<bndbox>
				<xmin>199</xmin>
				<ymin>146</ymin>
				<xmax>364</xmax>
				<ymax>320</ymax>
			</bndbox>
		</object>
		<object>
			<name>seaurchin</name>
			<pose>Rear</pose>
			<truncated>0</truncated>
			<difficult>0</difficult>
			<bndbox>
				<xmin>456</xmin>
				<ymin>96</ymin>
				<xmax>531</xmax>
				<ymax>171</ymax>
			</bndbox>
		</object>
		<object>
			<name>scallop</name>
			<pose>Rear</pose>
			<truncated>0</truncated>
			<difficult>0</difficult>
			<bndbox>
				<xmin>572</xmin>
				<ymin>216</ymin>
				<xmax>640</xmax>
				<ymax>284</ymax>
			</bndbox>
		</object>
		<object>
			<name>scallop</name>
			<pose>Rear</pose>
			<truncated>0</truncated>
			<difficult>0</difficult>
			<bndbox>
				<xmin>511</xmin>
				<ymin>153</ymin>
				<xmax>603</xmax>
				<ymax>224</ymax>
			</bndbox>
		</object>
		<object>
			<name>seacucumber</name>
			<pose>Rear</pose>
			<truncated>0</truncated>
			<difficult>0</difficult>
			<bndbox>
				<xmin>396</xmin>
				<ymin>3</ymin>
				<xmax>463</xmax>
				<ymax>38</ymax>
			</bndbox>
		</object>
		<object>
			<name>seacucumber</name>
			<pose>Rear</pose>
			<truncated>0</truncated>
			<difficult>0</difficult>
			<bndbox>
				<xmin>90</xmin>
				<ymin>97</ymin>
				<xmax>214</xmax>
				<ymax>166</ymax>
			</bndbox>
		</object>
		<object>
			<name>seacucumber</name>
			<pose>Rear</pose>
			<truncated>0</truncated>
			<difficult>0</difficult>
			<bndbox>
				<xmin>300</xmin>
				<ymin>26</ymin>
				<xmax>346</xmax>
				<ymax>85</ymax>
			</bndbox>
		</object>
		<object>
			<name>seacucumber</name>
			<pose>Rear</pose>
			<truncated>0</truncated>
			<difficult>0</difficult>
			<bndbox>
				<xmin>207</xmin>
				<ymin>56</ymin>
				<xmax>305</xmax>
				<ymax>136</ymax>
			</bndbox>
		</object>
		<object>
			<name>seacucumber</name>
			<pose>Rear</pose>
			<truncated>0</truncated>
			<difficult>0</difficult>
			<bndbox>
				<xmin>363</xmin>
				<ymin>313</ymin>
				<xmax>508</xmax>
				<ymax>403</ymax>
			</bndbox>
		</object>
	</annotation>
