<?xml version="1.0" encoding="utf-8"?>
	<annotation>
		<folder>VOC2007</folder>
		<filename>60300.jpg</filename>
		<size>
			<width>720</width>
			<height>405</height>
			<depth>3</depth>
		</size>
		<segmented>0</segmented>
		<object>
			<name>seacucumber</name>
			<pose>Rear</pose>
			<truncated>0</truncated>
			<difficult>0</difficult>
			<bndbox>
				<xmin>475</xmin>
				<ymin>279</ymin>
				<xmax>536</xmax>
				<ymax>313</ymax>
			</bndbox>
		</object>
		<object>
			<name>seacucumber</name>
			<pose>Rear</pose>
			<truncated>0</truncated>
			<difficult>0</difficult>
			<bndbox>
				<xmin>251</xmin>
				<ymin>55</ymin>
				<xmax>296</xmax>
				<ymax>80</ymax>
			</bndbox>
		</object>
		<object>
			<name>seacucumber</name>
			<pose>Rear</pose>
			<truncated>0</truncated>
			<difficult>0</difficult>
			<bndbox>
				<xmin>476</xmin>
				<ymin>91</ymin>
				<xmax>537</xmax>
				<ymax>123</ymax>
			</bndbox>
		</object>
		<object>
			<name>seacucumber</name>
			<pose>Rear</pose>
			<truncated>0</truncated>
			<difficult>0</difficult>
			<bndbox>
				<xmin>23</xmin>
				<ymin>45</ymin>
				<xmax>69</xmax>
				<ymax>74</ymax>
			</bndbox>
		</object>
		<object>
			<name>seacucumber</name>
			<pose>Rear</pose>
			<truncated>0</truncated>
			<difficult>0</difficult>
			<bndbox>
				<xmin>263</xmin>
				<ymin>38</ymin>
				<xmax>308</xmax>
				<ymax>71</ymax>
			</bndbox>
		</object>
		<object>
			<name>seacucumber</name>
			<pose>Rear</pose>
			<truncated>0</truncated>
			<difficult>0</difficult>
			<bndbox>
				<xmin>83</xmin>
				<ymin>31</ymin>
				<xmax>134</xmax>
				<ymax>62</ymax>
			</bndbox>
		</object>
		<object>
			<name>seacucumber</name>
			<pose>Rear</pose>
			<truncated>0</truncated>
			<difficult>0</difficult>
			<bndbox>
				<xmin>433</xmin>
				<ymin>13</ymin>
				<xmax>472</xmax>
				<ymax>64</ymax>
			</bndbox>
		</object>
		<object>
			<name>seacucumber</name>
			<pose>Rear</pose>
			<truncated>0</truncated>
			<difficult>0</difficult>
			<bndbox>
				<xmin>427</xmin>
				<ymin>26</ymin>
				<xmax>467</xmax>
				<ymax>70</ymax>
			</bndbox>
		</object>
		<object>
			<name>seacucumber</name>
			<pose>Rear</pose>
			<truncated>0</truncated>
			<difficult>0</difficult>
			<bndbox>
				<xmin>517</xmin>
				<ymin>20</ymin>
				<xmax>559</xmax>
				<ymax>49</ymax>
			</bndbox>
		</object>
		<object>
			<name>seacucumber</name>
			<pose>Rear</pose>
			<truncated>0</truncated>
			<difficult>0</difficult>
			<bndbox>
				<xmin>315</xmin>
				<ymin>34</ymin>
				<xmax>363</xmax>
				<ymax>66</ymax>
			</bndbox>
		</object>
		<object>
			<name>seacucumber</name>
			<pose>Rear</pose>
			<truncated>0</truncated>
			<difficult>0</difficult>
			<bndbox>
				<xmin>202</xmin>
				<ymin>107</ymin>
				<xmax>241</xmax>
				<ymax>145</ymax>
			</bndbox>
		</object>
		<object>
			<name>seacucumber</name>
			<pose>Rear</pose>
			<truncated>0</truncated>
			<difficult>0</difficult>
			<bndbox>
				<xmin>123</xmin>
				<ymin>79</ymin>
				<xmax>170</xmax>
				<ymax>129</ymax>
			</bndbox>
		</object>
		<object>
			<name>seacucumber</name>
			<pose>Rear</pose>
			<truncated>0</truncated>
			<difficult>0</difficult>
			<bndbox>
				<xmin>399</xmin>
				<ymin>330</ymin>
				<xmax>431</xmax>
				<ymax>364</ymax>
			</bndbox>
		</object>
		<object>
			<name>seacucumber</name>
			<pose>Rear</pose>
			<truncated>0</truncated>
			<difficult>0</difficult>
			<bndbox>
				<xmin>685</xmin>
				<ymin>380</ymin>
				<xmax>718</xmax>
				<ymax>404</ymax>
			</bndbox>
		</object>
		<object>
			<name>seacucumber</name>
			<pose>Rear</pose>
			<truncated>0</truncated>
			<difficult>0</difficult>
			<bndbox>
				<xmin>464</xmin>
				<ymin>299</ymin>
				<xmax>505</xmax>
				<ymax>353</ymax>
			</bndbox>
		</object>
		<object>
			<name>seacucumber</name>
			<pose>Rear</pose>
			<truncated>0</truncated>
			<difficult>0</difficult>
			<bndbox>
				<xmin>356</xmin>
				<ymin>210</ymin>
				<xmax>411</xmax>
				<ymax>243</ymax>
			</bndbox>
		</object>
		<object>
			<name>seacucumber</name>
			<pose>Rear</pose>
			<truncated>0</truncated>
			<difficult>0</difficult>
			<bndbox>
				<xmin>510</xmin>
				<ymin>271</ymin>
				<xmax>566</xmax>
				<ymax>303</ymax>
			</bndbox>
		</object>
		<object>
			<name>seacucumber</name>
			<pose>Rear</pose>
			<truncated>0</truncated>
			<difficult>0</difficult>
			<bndbox>
				<xmin>478</xmin>
				<ymin>207</ymin>
				<xmax>531</xmax>
				<ymax>234</ymax>
			</bndbox>
		</object>
		<object>
			<name>seacucumber</name>
			<pose>Rear</pose>
			<truncated>0</truncated>
			<difficult>0</difficult>
			<bndbox>
				<xmin>296</xmin>
				<ymin>182</ymin>
				<xmax>355</xmax>
				<ymax>209</ymax>
			</bndbox>
		</object>
		<object>
			<name>seacucumber</name>
			<pose>Rear</pose>
			<truncated>0</truncated>
			<difficult>0</difficult>
			<bndbox>
				<xmin>356</xmin>
				<ymin>168</ymin>
				<xmax>410</xmax>
				<ymax>209</ymax>
			</bndbox>
		</object>
	</annotation>
