<?xml version="1.0" encoding="utf-8"?>
	<annotation>
		<folder>VOC2007</folder>
		<filename>60943.jpg</filename>
		<size>
			<width>720</width>
			<height>405</height>
			<depth>3</depth>
		</size>
		<segmented>0</segmented>
		<object>
			<name>scallop</name>
			<pose>Rear</pose>
			<truncated>0</truncated>
			<difficult>0</difficult>
			<bndbox>
				<xmin>450</xmin>
				<ymin>384</ymin>
				<xmax>520</xmax>
				<ymax>403</ymax>
			</bndbox>
		</object>
		<object>
			<name>seaurchin</name>
			<pose>Rear</pose>
			<truncated>0</truncated>
			<difficult>0</difficult>
			<bndbox>
				<xmin>400</xmin>
				<ymin>386</ymin>
				<xmax>469</xmax>
				<ymax>403</ymax>
			</bndbox>
		</object>
		<object>
			<name>seacucumber</name>
			<pose>Rear</pose>
			<truncated>0</truncated>
			<difficult>0</difficult>
			<bndbox>
				<xmin>125</xmin>
				<ymin>385</ymin>
				<xmax>253</xmax>
				<ymax>403</ymax>
			</bndbox>
		</object>
		<object>
			<name>seacucumber</name>
			<pose>Rear</pose>
			<truncated>0</truncated>
			<difficult>0</difficult>
			<bndbox>
				<xmin>369</xmin>
				<ymin>390</ymin>
				<xmax>457</xmax>
				<ymax>403</ymax>
			</bndbox>
		</object>
		<object>
			<name>seacucumber</name>
			<pose>Rear</pose>
			<truncated>0</truncated>
			<difficult>0</difficult>
			<bndbox>
				<xmin>450</xmin>
				<ymin>347</ymin>
				<xmax>642</xmax>
				<ymax>403</ymax>
			</bndbox>
		</object>
		<object>
			<name>seacucumber</name>
			<pose>Rear</pose>
			<truncated>0</truncated>
			<difficult>0</difficult>
			<bndbox>
				<xmin>699</xmin>
				<ymin>259</ymin>
				<xmax>719</xmax>
				<ymax>337</ymax>
			</bndbox>
		</object>
		<object>
			<name>seaurchin</name>
			<pose>Rear</pose>
			<truncated>0</truncated>
			<difficult>0</difficult>
			<bndbox>
				<xmin>704</xmin>
				<ymin>147</ymin>
				<xmax>719</xmax>
				<ymax>196</ymax>
			</bndbox>
		</object>
		<object>
			<name>seaurchin</name>
			<pose>Rear</pose>
			<truncated>0</truncated>
			<difficult>0</difficult>
			<bndbox>
				<xmin>396</xmin>
				<ymin>81</ymin>
				<xmax>453</xmax>
				<ymax>128</ymax>
			</bndbox>
		</object>
		<object>
			<name>seaurchin</name>
			<pose>Rear</pose>
			<truncated>0</truncated>
			<difficult>0</difficult>
			<bndbox>
				<xmin>330</xmin>
				<ymin>153</ymin>
				<xmax>402</xmax>
				<ymax>220</ymax>
			</bndbox>
		</object>
		<object>
			<name>seaurchin</name>
			<pose>Rear</pose>
			<truncated>0</truncated>
			<difficult>0</difficult>
			<bndbox>
				<xmin>267</xmin>
				<ymin>361</ymin>
				<xmax>347</xmax>
				<ymax>403</ymax>
			</bndbox>
		</object>
		<object>
			<name>scallop</name>
			<pose>Rear</pose>
			<truncated>0</truncated>
			<difficult>0</difficult>
			<bndbox>
				<xmin>109</xmin>
				<ymin>323</ymin>
				<xmax>193</xmax>
				<ymax>402</ymax>
			</bndbox>
		</object>
		<object>
			<name>seacucumber</name>
			<pose>Rear</pose>
			<truncated>0</truncated>
			<difficult>0</difficult>
			<bndbox>
				<xmin>27</xmin>
				<ymin>325</ymin>
				<xmax>109</xmax>
				<ymax>403</ymax>
			</bndbox>
		</object>
		<object>
			<name>scallop</name>
			<pose>Rear</pose>
			<truncated>0</truncated>
			<difficult>0</difficult>
			<bndbox>
				<xmin>237</xmin>
				<ymin>47</ymin>
				<xmax>295</xmax>
				<ymax>95</ymax>
			</bndbox>
		</object>
		<object>
			<name>scallop</name>
			<pose>Rear</pose>
			<truncated>0</truncated>
			<difficult>0</difficult>
			<bndbox>
				<xmin>699</xmin>
				<ymin>352</ymin>
				<xmax>715</xmax>
				<ymax>403</ymax>
			</bndbox>
		</object>
		<object>
			<name>scallop</name>
			<pose>Rear</pose>
			<truncated>0</truncated>
			<difficult>0</difficult>
			<bndbox>
				<xmin>95</xmin>
				<ymin>139</ymin>
				<xmax>153</xmax>
				<ymax>183</ymax>
			</bndbox>
		</object>
		<object>
			<name>scallop</name>
			<pose>Rear</pose>
			<truncated>0</truncated>
			<difficult>0</difficult>
			<bndbox>
				<xmin>11</xmin>
				<ymin>178</ymin>
				<xmax>71</xmax>
				<ymax>228</ymax>
			</bndbox>
		</object>
		<object>
			<name>scallop</name>
			<pose>Rear</pose>
			<truncated>0</truncated>
			<difficult>0</difficult>
			<bndbox>
				<xmin>573</xmin>
				<ymin>0</ymin>
				<xmax>643</xmax>
				<ymax>23</ymax>
			</bndbox>
		</object>
		<object>
			<name>scallop</name>
			<pose>Rear</pose>
			<truncated>0</truncated>
			<difficult>0</difficult>
			<bndbox>
				<xmin>384</xmin>
				<ymin>208</ymin>
				<xmax>462</xmax>
				<ymax>335</ymax>
			</bndbox>
		</object>
		<object>
			<name>seacucumber</name>
			<pose>Rear</pose>
			<truncated>0</truncated>
			<difficult>0</difficult>
			<bndbox>
				<xmin>395</xmin>
				<ymin>131</ymin>
				<xmax>458</xmax>
				<ymax>175</ymax>
			</bndbox>
		</object>
		<object>
			<name>scallop</name>
			<pose>Rear</pose>
			<truncated>0</truncated>
			<difficult>0</difficult>
			<bndbox>
				<xmin>476</xmin>
				<ymin>0</ymin>
				<xmax>533</xmax>
				<ymax>14</ymax>
			</bndbox>
		</object>
		<object>
			<name>seacucumber</name>
			<pose>Rear</pose>
			<truncated>0</truncated>
			<difficult>0</difficult>
			<bndbox>
				<xmin>567</xmin>
				<ymin>194</ymin>
				<xmax>669</xmax>
				<ymax>250</ymax>
			</bndbox>
		</object>
		<object>
			<name>scallop</name>
			<pose>Rear</pose>
			<truncated>0</truncated>
			<difficult>0</difficult>
			<bndbox>
				<xmin>189</xmin>
				<ymin>93</ymin>
				<xmax>255</xmax>
				<ymax>138</ymax>
			</bndbox>
		</object>
		<object>
			<name>seacucumber</name>
			<pose>Rear</pose>
			<truncated>0</truncated>
			<difficult>0</difficult>
			<bndbox>
				<xmin>310</xmin>
				<ymin>216</ymin>
				<xmax>377</xmax>
				<ymax>354</ymax>
			</bndbox>
		</object>
		<object>
			<name>seacucumber</name>
			<pose>Rear</pose>
			<truncated>0</truncated>
			<difficult>0</difficult>
			<bndbox>
				<xmin>230</xmin>
				<ymin>207</ymin>
				<xmax>329</xmax>
				<ymax>266</ymax>
			</bndbox>
		</object>
		<object>
			<name>seacucumber</name>
			<pose>Rear</pose>
			<truncated>0</truncated>
			<difficult>0</difficult>
			<bndbox>
				<xmin>147</xmin>
				<ymin>265</ymin>
				<xmax>317</xmax>
				<ymax>325</ymax>
			</bndbox>
		</object>
		<object>
			<name>scallop</name>
			<pose>Rear</pose>
			<truncated>0</truncated>
			<difficult>0</difficult>
			<bndbox>
				<xmin>501</xmin>
				<ymin>99</ymin>
				<xmax>592</xmax>
				<ymax>163</ymax>
			</bndbox>
		</object>
		<object>
			<name>scallop</name>
			<pose>Rear</pose>
			<truncated>0</truncated>
			<difficult>0</difficult>
			<bndbox>
				<xmin>690</xmin>
				<ymin>176</ymin>
				<xmax>719</xmax>
				<ymax>251</ymax>
			</bndbox>
		</object>
		<object>
			<name>scallop</name>
			<pose>Rear</pose>
			<truncated>0</truncated>
			<difficult>0</difficult>
			<bndbox>
				<xmin>676</xmin>
				<ymin>260</ymin>
				<xmax>718</xmax>
				<ymax>333</ymax>
			</bndbox>
		</object>
		<object>
			<name>scallop</name>
			<pose>Rear</pose>
			<truncated>0</truncated>
			<difficult>0</difficult>
			<bndbox>
				<xmin>455</xmin>
				<ymin>149</ymin>
				<xmax>532</xmax>
				<ymax>201</ymax>
			</bndbox>
		</object>
		<object>
			<name>scallop</name>
			<pose>Rear</pose>
			<truncated>0</truncated>
			<difficult>0</difficult>
			<bndbox>
				<xmin>464</xmin>
				<ymin>73</ymin>
				<xmax>526</xmax>
				<ymax>119</ymax>
			</bndbox>
		</object>
		<object>
			<name>seaurchin</name>
			<pose>Rear</pose>
			<truncated>0</truncated>
			<difficult>0</difficult>
			<bndbox>
				<xmin>584</xmin>
				<ymin>254</ymin>
				<xmax>680</xmax>
				<ymax>348</ymax>
			</bndbox>
		</object>
		<object>
			<name>seaurchin</name>
			<pose>Rear</pose>
			<truncated>0</truncated>
			<difficult>0</difficult>
			<bndbox>
				<xmin>500</xmin>
				<ymin>234</ymin>
				<xmax>582</xmax>
				<ymax>313</ymax>
			</bndbox>
		</object>
	</annotation>
