<?xml version="1.0" encoding="utf-8"?>
	<annotation>
		<folder>VOC2007</folder>
		<filename>61768.jpg</filename>
		<size>
			<width>720</width>
			<height>405</height>
			<depth>3</depth>
		</size>
		<segmented>0</segmented>
		<object>
			<name>scallop</name>
			<pose>Rear</pose>
			<truncated>0</truncated>
			<difficult>0</difficult>
			<bndbox>
				<xmin>307</xmin>
				<ymin>381</ymin>
				<xmax>454</xmax>
				<ymax>403</ymax>
			</bndbox>
		</object>
		<object>
			<name>scallop</name>
			<pose>Rear</pose>
			<truncated>0</truncated>
			<difficult>0</difficult>
			<bndbox>
				<xmin>455</xmin>
				<ymin>375</ymin>
				<xmax>606</xmax>
				<ymax>403</ymax>
			</bndbox>
		</object>
		<object>
			<name>seacucumber</name>
			<pose>Rear</pose>
			<truncated>0</truncated>
			<difficult>0</difficult>
			<bndbox>
				<xmin>0</xmin>
				<ymin>374</ymin>
				<xmax>87</xmax>
				<ymax>403</ymax>
			</bndbox>
		</object>
		<object>
			<name>seaurchin</name>
			<pose>Rear</pose>
			<truncated>0</truncated>
			<difficult>0</difficult>
			<bndbox>
				<xmin>299</xmin>
				<ymin>389</ymin>
				<xmax>420</xmax>
				<ymax>402</ymax>
			</bndbox>
		</object>
		<object>
			<name>scallop</name>
			<pose>Rear</pose>
			<truncated>0</truncated>
			<difficult>0</difficult>
			<bndbox>
				<xmin>0</xmin>
				<ymin>357</ymin>
				<xmax>37</xmax>
				<ymax>403</ymax>
			</bndbox>
		</object>
		<object>
			<name>scallop</name>
			<pose>Rear</pose>
			<truncated>0</truncated>
			<difficult>0</difficult>
			<bndbox>
				<xmin>0</xmin>
				<ymin>324</ymin>
				<xmax>76</xmax>
				<ymax>403</ymax>
			</bndbox>
		</object>
		<object>
			<name>seacucumber</name>
			<pose>Rear</pose>
			<truncated>0</truncated>
			<difficult>0</difficult>
			<bndbox>
				<xmin>317</xmin>
				<ymin>384</ymin>
				<xmax>502</xmax>
				<ymax>403</ymax>
			</bndbox>
		</object>
		<object>
			<name>seaurchin</name>
			<pose>Rear</pose>
			<truncated>0</truncated>
			<difficult>0</difficult>
			<bndbox>
				<xmin>6</xmin>
				<ymin>370</ymin>
				<xmax>86</xmax>
				<ymax>403</ymax>
			</bndbox>
		</object>
		<object>
			<name>seacucumber</name>
			<pose>Rear</pose>
			<truncated>0</truncated>
			<difficult>0</difficult>
			<bndbox>
				<xmin>79</xmin>
				<ymin>399</ymin>
				<xmax>245</xmax>
				<ymax>403</ymax>
			</bndbox>
		</object>
		<object>
			<name>scallop</name>
			<pose>Rear</pose>
			<truncated>0</truncated>
			<difficult>0</difficult>
			<bndbox>
				<xmin>12</xmin>
				<ymin>383</ymin>
				<xmax>142</xmax>
				<ymax>403</ymax>
			</bndbox>
		</object>
		<object>
			<name>seacucumber</name>
			<pose>Rear</pose>
			<truncated>0</truncated>
			<difficult>0</difficult>
			<bndbox>
				<xmin>34</xmin>
				<ymin>355</ymin>
				<xmax>120</xmax>
				<ymax>402</ymax>
			</bndbox>
		</object>
		<object>
			<name>seacucumber</name>
			<pose>Rear</pose>
			<truncated>0</truncated>
			<difficult>0</difficult>
			<bndbox>
				<xmin>507</xmin>
				<ymin>388</ymin>
				<xmax>601</xmax>
				<ymax>403</ymax>
			</bndbox>
		</object>
		<object>
			<name>scallop</name>
			<pose>Rear</pose>
			<truncated>0</truncated>
			<difficult>0</difficult>
			<bndbox>
				<xmin>0</xmin>
				<ymin>72</ymin>
				<xmax>16</xmax>
				<ymax>140</ymax>
			</bndbox>
		</object>
		<object>
			<name>seacucumber</name>
			<pose>Rear</pose>
			<truncated>0</truncated>
			<difficult>0</difficult>
			<bndbox>
				<xmin>0</xmin>
				<ymin>161</ymin>
				<xmax>13</xmax>
				<ymax>267</ymax>
			</bndbox>
		</object>
		<object>
			<name>scallop</name>
			<pose>Rear</pose>
			<truncated>0</truncated>
			<difficult>0</difficult>
			<bndbox>
				<xmin>144</xmin>
				<ymin>244</ymin>
				<xmax>235</xmax>
				<ymax>352</ymax>
			</bndbox>
		</object>
		<object>
			<name>scallop</name>
			<pose>Rear</pose>
			<truncated>0</truncated>
			<difficult>0</difficult>
			<bndbox>
				<xmin>155</xmin>
				<ymin>323</ymin>
				<xmax>324</xmax>
				<ymax>403</ymax>
			</bndbox>
		</object>
		<object>
			<name>seaurchin</name>
			<pose>Rear</pose>
			<truncated>0</truncated>
			<difficult>0</difficult>
			<bndbox>
				<xmin>41</xmin>
				<ymin>131</ymin>
				<xmax>122</xmax>
				<ymax>218</ymax>
			</bndbox>
		</object>
		<object>
			<name>seacucumber</name>
			<pose>Rear</pose>
			<truncated>0</truncated>
			<difficult>0</difficult>
			<bndbox>
				<xmin>289</xmin>
				<ymin>392</ymin>
				<xmax>384</xmax>
				<ymax>403</ymax>
			</bndbox>
		</object>
		<object>
			<name>scallop</name>
			<pose>Rear</pose>
			<truncated>0</truncated>
			<difficult>0</difficult>
			<bndbox>
				<xmin>132</xmin>
				<ymin>137</ymin>
				<xmax>213</xmax>
				<ymax>213</ymax>
			</bndbox>
		</object>
		<object>
			<name>seacucumber</name>
			<pose>Rear</pose>
			<truncated>0</truncated>
			<difficult>0</difficult>
			<bndbox>
				<xmin>210</xmin>
				<ymin>142</ymin>
				<xmax>304</xmax>
				<ymax>319</ymax>
			</bndbox>
		</object>
		<object>
			<name>scallop</name>
			<pose>Rear</pose>
			<truncated>0</truncated>
			<difficult>0</difficult>
			<bndbox>
				<xmin>479</xmin>
				<ymin>366</ymin>
				<xmax>624</xmax>
				<ymax>400</ymax>
			</bndbox>
		</object>
		<object>
			<name>seacucumber</name>
			<pose>Rear</pose>
			<truncated>0</truncated>
			<difficult>0</difficult>
			<bndbox>
				<xmin>499</xmin>
				<ymin>270</ymin>
				<xmax>719</xmax>
				<ymax>371</ymax>
			</bndbox>
		</object>
		<object>
			<name>scallop</name>
			<pose>Rear</pose>
			<truncated>0</truncated>
			<difficult>0</difficult>
			<bndbox>
				<xmin>643</xmin>
				<ymin>193</ymin>
				<xmax>718</xmax>
				<ymax>300</ymax>
			</bndbox>
		</object>
		<object>
			<name>seacucumber</name>
			<pose>Rear</pose>
			<truncated>0</truncated>
			<difficult>0</difficult>
			<bndbox>
				<xmin>409</xmin>
				<ymin>358</ymin>
				<xmax>489</xmax>
				<ymax>403</ymax>
			</bndbox>
		</object>
		<object>
			<name>scallop</name>
			<pose>Rear</pose>
			<truncated>0</truncated>
			<difficult>0</difficult>
			<bndbox>
				<xmin>431</xmin>
				<ymin>110</ymin>
				<xmax>496</xmax>
				<ymax>151</ymax>
			</bndbox>
		</object>
		<object>
			<name>scallop</name>
			<pose>Rear</pose>
			<truncated>0</truncated>
			<difficult>0</difficult>
			<bndbox>
				<xmin>438</xmin>
				<ymin>40</ymin>
				<xmax>511</xmax>
				<ymax>84</ymax>
			</bndbox>
		</object>
		<object>
			<name>scallop</name>
			<pose>Rear</pose>
			<truncated>0</truncated>
			<difficult>0</difficult>
			<bndbox>
				<xmin>221</xmin>
				<ymin>57</ymin>
				<xmax>285</xmax>
				<ymax>103</ymax>
			</bndbox>
		</object>
		<object>
			<name>seacucumber</name>
			<pose>Rear</pose>
			<truncated>0</truncated>
			<difficult>0</difficult>
			<bndbox>
				<xmin>502</xmin>
				<ymin>94</ymin>
				<xmax>593</xmax>
				<ymax>162</ymax>
			</bndbox>
		</object>
		<object>
			<name>seacucumber</name>
			<pose>Rear</pose>
			<truncated>0</truncated>
			<difficult>0</difficult>
			<bndbox>
				<xmin>513</xmin>
				<ymin>31</ymin>
				<xmax>611</xmax>
				<ymax>126</ymax>
			</bndbox>
		</object>
		<object>
			<name>seaurchin</name>
			<pose>Rear</pose>
			<truncated>0</truncated>
			<difficult>0</difficult>
			<bndbox>
				<xmin>311</xmin>
				<ymin>305</ymin>
				<xmax>416</xmax>
				<ymax>391</ymax>
			</bndbox>
		</object>
		<object>
			<name>seaurchin</name>
			<pose>Rear</pose>
			<truncated>0</truncated>
			<difficult>0</difficult>
			<bndbox>
				<xmin>192</xmin>
				<ymin>90</ymin>
				<xmax>258</xmax>
				<ymax>150</ymax>
			</bndbox>
		</object>
		<object>
			<name>seaurchin</name>
			<pose>Rear</pose>
			<truncated>0</truncated>
			<difficult>0</difficult>
			<bndbox>
				<xmin>371</xmin>
				<ymin>138</ymin>
				<xmax>436</xmax>
				<ymax>202</ymax>
			</bndbox>
		</object>
		<object>
			<name>seaurchin</name>
			<pose>Rear</pose>
			<truncated>0</truncated>
			<difficult>0</difficult>
			<bndbox>
				<xmin>397</xmin>
				<ymin>235</ymin>
				<xmax>503</xmax>
				<ymax>343</ymax>
			</bndbox>
		</object>
		<object>
			<name>seaurchin</name>
			<pose>Rear</pose>
			<truncated>0</truncated>
			<difficult>0</difficult>
			<bndbox>
				<xmin>45</xmin>
				<ymin>217</ymin>
				<xmax>127</xmax>
				<ymax>294</ymax>
			</bndbox>
		</object>
		<object>
			<name>seaurchin</name>
			<pose>Rear</pose>
			<truncated>0</truncated>
			<difficult>0</difficult>
			<bndbox>
				<xmin>324</xmin>
				<ymin>68</ymin>
				<xmax>393</xmax>
				<ymax>125</ymax>
			</bndbox>
		</object>
	</annotation>
